pytest_extensions/__init__.py
pytest_extensions/comparators/__init__.py
pytest_extensions/comparators/dates.py
pytest_extensions/comparators/strings.py
pytest_extensions/comparators/types.py
pytest_extensions/nested/__init__.py
pytest_extensions-0.0.1.dist-info/LICENSE.txt
pytest_extensions-0.0.1.dist-info/METADATA
pytest_extensions-0.0.1.dist-info/WHEEL
pytest_extensions-0.0.1.dist-info/top_level.txt
pytest_extensions-0.0.1.dist-info/RECORD
