Metadata-Version: 2.1
Name: pytest-extensions
Version: 0.0.1
Summary: A collection of helpers for pytest to ease testing
Home-page: https://gitlab.com/too-many-programmers/pytest-extensions
Author: Benjamin Rigaud
Author-email: ben.open.source@gmail.com
License: MIT
Project-URL: Documentation, https://gitlab.com/too-many-programmers/pytest-extensions
Project-URL: Source, https://gitlab.com/too-many-programmers/pytest-extensions
Project-URL: Tracker, https://gitlab.com/too-many-programmers/pytest-extensions/-/issues
Platform: any
Classifier: Development Status :: 4 - Beta
Classifier: Programming Language :: Python
Classifier: Framework :: Pytest
Classifier: Topic :: Software Development :: Testing
License-File: LICENSE.txt
Requires-Dist: importlib-metadata ; python_version < "3.8"
Provides-Extra: testing
Requires-Dist: setuptools ; extra == 'testing'
Requires-Dist: pytest ; extra == 'testing'
Requires-Dist: pytest-cov ; extra == 'testing'
